kapsula.py
kapsula-0.2.1.dist-info/LICENSE
kapsula-0.2.1.dist-info/METADATA
kapsula-0.2.1.dist-info/WHEEL
kapsula-0.2.1.dist-info/entry_points.txt
kapsula-0.2.1.dist-info/top_level.txt
kapsula-0.2.1.dist-info/RECORD
