Metadata-Version: 2.2
Name: kapsula
Version: 0.2.1
Summary: Great for adding markdown docs to llm. Dead simple docs generator. Originally used at Metabob.com
Author: ARJ
Project-URL: Homepage, https://github.com/Abdur-RahmaanJ/kapsula
Project-URL: Documentation, https://github.com/Abdur-RahmaanJ/kapsula
Project-URL: Source Code, https://github.com/Abdur-RahmaanJ/kapsula
Project-URL: Bug Tracker, https://github.com/Abdur-RahmaanJ/kapsula/issues
Classifier: Programming Language :: Python :: 3
Classifier: Programming Language :: Python :: 3.9
Classifier: Programming Language :: Python :: 3.10
Classifier: Programming Language :: Python :: 3.11
Classifier: Programming Language :: Python :: 3.12
Classifier: Programming Language :: Python :: 3.13
Classifier: License :: OSI Approved :: MIT License
Classifier: Operating System :: OS Independent
Classifier: Topic :: Documentation
Classifier: Topic :: Software Development :: Documentation
Classifier: Topic :: Text Processing :: Markup :: Markdown
License-File: LICENSE
